naimco/__init__.py
naimco/connection.py
naimco/controllers.py
naimco/core.py
naimco/msg_processing.py
naimco/scripts/naim_control.py
naimco/scripts/run1.py
naimco-0.4.0.dist-info/METADATA
naimco-0.4.0.dist-info/WHEEL
naimco-0.4.0.dist-info/entry_points.txt
naimco-0.4.0.dist-info/licenses/LICENSE
naimco-0.4.0.dist-info/RECORD
