Metadata-Version: 2.4
Name: naimco
Version: 0.4.0
Summary: Package to control Naim Mu-so sound systems
License: MIT
License-File: LICENSE
Keywords: naim,mu-so,homeassistant
Author: Yngvi Þór Sigurjónsson
Author-email: blitzkopf@gmail.com
Requires-Python: >=3.11,<4.0
Classifier: Development Status :: 3 - Alpha
Classifier: License :: OSI Approved :: MIT License
Classifier: Programming Language :: Python :: 3
Classifier: Programming Language :: Python :: 3.11
Classifier: Programming Language :: Python :: 3.12
Classifier: Programming Language :: Python :: 3.13
Classifier: Programming Language :: Python :: 3.14
Classifier: Topic :: Home Automation
Classifier: Topic :: Multimedia :: Sound/Audio :: Players
Requires-Dist: argparse (>=1.4.0,<2.0.0)
Requires-Dist: asyncio (>=3.4.3,<5.0.0)
Project-URL: Homepage, https://github.com/blitzkopf/NaimCo
Project-URL: Repository, https://github.com/blitzkopf/NaimCo
